{"nodeIndex":1,"featureIndex":1,"threshold":127.5,"label":null,"left":{"nodeIndex":2,"featureIndex":1,"threshold":99.5,"label":null,"left":{"nodeIndex":3,"featureIndex":0,"threshold":4.5,"label":null,"left":{"nodeIndex":4,"featureIndex":6,"threshold":0.253,"label":null,"left":{"nodeIndex":5,"featureIndex":6,"threshold":0.245,"label":null,"left":{"nodeIndex":6,"featureIndex":-1,"threshold":0,"label":0,"left":null,"right":null},"right":{"nodeIndex":7,"featureIndex":1,"threshold":75.5,"label":null,"left":{"nodeIndex":8,"featureIndex":-1,"threshold":0,"label":0,"left":null,"right":null},"right":{"nodeIndex":9,"featureIndex":-1,"threshold":0,"label":1,"left":null,"right":null}}},"right":{"nodeIndex":10,"featureIndex":-1,"threshold":0,"label":0,"left":null,"right":null}},"right":{"nodeIndex":11,"featureIndex":1,"threshold":28.5,"label":null,"left":{"nodeIndex":12,"featureIndex":-1,"threshold":0,"label":1,"left":null,"right":null},"right":{"nodeIndex":13,"featureIndex":6,"threshold":1.1105,"label":null,"left":{"nodeIndex":14,"featureIndex":0,"threshold":11.5,"label":null,"left":{"nodeIndex":15,"featureIndex":-1,"threshold":0,"label":0,"left":null,"right":null},"right":{"nodeIndex":16,"featureIndex":5,"threshold":31.25,"label":null,"left":{"nodeIndex":17,"featureIndex":-1,"threshold":0,"label":1,"left":null,"right":null},"right":{"nodeIndex":18,"featureIndex":-1,"threshold":0,"label":0,"left":null,"right":null}}},"right":{"nodeIndex":19,"featureIndex":-1,"threshold":0,"label":1,"left":null,"right":null}}}},"right":{"nodeIndex":20,"featureIndex":5,"threshold":26.4,"label":null,"left":{"nodeIndex":21,"featureIndex":6,"threshold":0.625,"label":null,"left":{"nodeIndex":22,"featureIndex":-1,"threshold":0,"label":0,"left":null,"right":null},"right":{"nodeIndex":23,"featureIndex":6,"threshold":0.7455,"label":null,"left":{"nodeIndex":24,"featureIndex":-1,"threshold":0,"label":1,"left":null,"right":null},"right":{"nodeIndex":25,"featureIndex":-1,"threshold":0,"label":0,"left":null,"right":null}}},"right":{"nodeIndex":26,"featureIndex":7,"threshold":34.5,"label":null,"left":{"nodeIndex":27,"featureIndex":5,"threshold":32.7,"label":null,"left":{"nodeIndex":28,"featureIndex":0,"threshold":6.5,"label":null,"left":{"nodeIndex":29,"featureIndex":-1,"threshold":0,"label":0,"left":null,"right":null},"right":{"nodeIndex":30,"featureIndex":-1,"threshold":0,"label":1,"left":null,"right":null}},"right":{"nodeIndex":31,"featureIndex":5,"threshold":34.85,"label":null,"left":{"nodeIndex":32,"featureIndex":0,"threshold":4.5,"label":null,"left":{"nodeIndex":33,"featureIndex":6,"threshold":0.5285,"label":null,"left":{"nodeIndex":34,"featureIndex":0,"threshold":0.5,"label":null,"left":{"nodeIndex":35,"featureIndex":-1,"threshold":0,"label":1,"left":null,"right":null},"right":{"nodeIndex":36,"featureIndex":-1,"threshold":0,"label":0,"left":null,"right":null}},"right":{"nodeIndex":37,"featureIndex":-1,"threshold":0,"label":1,"left":null,"right":null}},"right":{"nodeIndex":38,"featureIndex":-1,"threshold":0,"label":0,"left":null,"right":null}},"right":{"nodeIndex":39,"featureIndex":4,"threshold":115,"label":null,"left":{"nodeIndex":40,"featureIndex":-1,"threshold":0,"label":0,"left":null,"right":null},"right":{"nodeIndex":41,"featureIndex":5,"threshold":45.4,"label":null,"left":{"nodeIndex":42,"featureIndex":2,"threshold":67,"label":null,"left":{"nodeIndex":43,"featureIndex":0,"threshold":0.5,"label":null,"left":{"nodeIndex":44,"featureIndex":-1,"threshold":0,"label":0,"left":null,"right":null},"right":{"nodeIndex":45,"featureIndex":-1,"threshold":0,"label":1,"left":null,"right":null}},"right":{"nodeIndex":46,"featureIndex":-1,"threshold":0,"label":0,"left":null,"right":null}},"right":{"nodeIndex":47,"featureIndex":-1,"threshold":0,"label":1,"left":null,"right":null}}}}},"right":{"nodeIndex":48,"featureIndex":6,"threshold":0.6035,"label":null,"left":{"nodeIndex":49,"featureIndex":6,"threshold":0.2735,"label":null,"left":{"nodeIndex":50,"featureIndex":1,"threshold":111,"label":null,"left":{"nodeIndex":51,"featureIndex":2,"threshold":78,"label":null,"left":{"nodeIndex":52,"featureIndex":-1,"threshold":0,"label":0,"left":null,"right":null},"right":{"nodeIndex":53,"featureIndex":0,"threshold":1,"label":null,"left":{"nodeIndex":54,"featureIndex":-1,"threshold":0,"label":0,"left":null,"right":null},"right":{"nodeIndex":55,"featureIndex":-1,"threshold":0,"label":1,"left":null,"right":null}}},"right":{"nodeIndex":56,"featureIndex":-1,"threshold":0,"label":1,"left":null,"right":null}},"right":{"nodeIndex":57,"featureIndex":0,"threshold":3,"label":null,"left":{"nodeIndex":58,"featureIndex":-1,"threshold":0,"label":1,"left":null,"right":null},"right":{"nodeIndex":59,"featureIndex":-1,"threshold":0,"label":0,"left":null,"right":null}}},"right":{"nodeIndex":60,"featureIndex":2,"threshold":90,"label":null,"left":{"nodeIndex":61,"featureIndex":-1,"threshold":0,"label":1,"left":null,"right":null},"right":{"nodeIndex":62,"featureIndex":-1,"threshold":0,"label":0,"left":null,"right":null}}}}}},"right":{"nodeIndex":63,"featureIndex":5,"threshold":29.95,"label":null,"left":{"nodeIndex":64,"featureIndex":1,"threshold":151.5,"label":null,"left":{"nodeIndex":65,"featureIndex":2,"threshold":73,"label":null,"left":{"nodeIndex":66,"featureIndex":4,"threshold":127.5,"label":null,"left":{"nodeIndex":67,"featureIndex":0,"threshold":5,"label":null,"left":{"nodeIndex":68,"featureIndex":-1,"threshold":0,"label":1,"left":null,"right":null},"right":{"nodeIndex":69,"featureIndex":-1,"threshold":0,"label":0,"left":null,"right":null}},"right":{"nodeIndex":70,"featureIndex":-1,"threshold":0,"label":0,"left":null,"right":null}},"right":{"nodeIndex":71,"featureIndex":-1,"threshold":0,"label":0,"left":null,"right":null}},"right":{"nodeIndex":72,"featureIndex":7,"threshold":61,"label":null,"left":{"nodeIndex":73,"featureIndex":0,"threshold":1.5,"label":null,"left":{"nodeIndex":74,"featureIndex":-1,"threshold":0,"label":0,"left":null,"right":null},"right":{"nodeIndex":75,"featureIndex":-1,"threshold":0,"label":1,"left":null,"right":null}},"right":{"nodeIndex":76,"featureIndex":-1,"threshold":0,"label":0,"left":null,"right":null}}},"right":{"nodeIndex":77,"featureIndex":1,"threshold":155,"label":null,"left":{"nodeIndex":78,"featureIndex":1,"threshold":152.5,"label":null,"left":{"nodeIndex":79,"featureIndex":6,"threshold":0.2625,"label":null,"left":{"nodeIndex":80,"featureIndex":1,"threshold":136.5,"label":null,"left":{"nodeIndex":81,"featureIndex":1,"threshold":130,"label":null,"left":{"nodeIndex":82,"featureIndex":-1,"threshold":0,"label":0,"left":null,"right":null},"right":{"nodeIndex":83,"featureIndex":-1,"threshold":0,"label":1,"left":null,"right":null}},"right":{"nodeIndex":84,"featureIndex":-1,"threshold":0,"label":0,"left":null,"right":null}},"right":{"nodeIndex":85,"featureIndex":0,"threshold":2.5,"label":null,"left":{"nodeIndex":86,"featureIndex":1,"threshold":141.5,"label":null,"left":{"nodeIndex":87,"featureIndex":0,"threshold":1.5,"label":null,"left":{"nodeIndex":88,"featureIndex":-1,"threshold":0,"label":1,"left":null,"right":null},"right":{"nodeIndex":89,"featureIndex":-1,"threshold":0,"label":0,"left":null,"right":null}},"right":{"nodeIndex":90,"featureIndex":2,"threshold":73,"label":null,"left":{"nodeIndex":91,"featureIndex":-1,"threshold":0,"label":1,"left":null,"right":null},"right":{"nodeIndex":92,"featureIndex":1,"threshold":148.5,"label":null,"left":{"nodeIndex":93,"featureIndex":-1,"threshold":0,"label":0,"left":null,"right":null},"right":{"nodeIndex":94,"featureIndex":-1,"threshold":0,"label":1,"left":null,"right":null}}}},"right":{"nodeIndex":95,"featureIndex":4,"threshold":333.5,"label":null,"left":{"nodeIndex":96,"featureIndex":-1,"threshold":0,"label":1,"left":null,"right":null},"right":{"nodeIndex":97,"featureIndex":-1,"threshold":0,"label":0,"left":null,"right":null}}}},"right":{"nodeIndex":98,"featureIndex":-1,"threshold":0,"label":0,"left":null,"right":null}},"right":{"nodeIndex":99,"featureIndex":6,"threshold":0.3425,"label":null,"left":{"nodeIndex":100,"featureIndex":5,"threshold":35.4,"label":null,"left":{"nodeIndex":101,"featureIndex":5,"threshold":33.8,"label":null,"left":{"nodeIndex":102,"featureIndex":0,"threshold":1.5,"label":null,"left":{"nodeIndex":103,"featureIndex":-1,"threshold":0,"label":0,"left":null,"right":null},"right":{"nodeIndex":104,"featureIndex":-1,"threshold":0,"label":1,"left":null,"right":null}},"right":{"nodeIndex":105,"featureIndex":0,"threshold":2,"label":null,"left":{"nodeIndex":106,"featureIndex":-1,"threshold":0,"label":1,"left":null,"right":null},"right":{"nodeIndex":107,"featureIndex":-1,"threshold":0,"label":0,"left":null,"right":null}}},"right":{"nodeIndex":108,"featureIndex":-1,"threshold":0,"label":1,"left":null,"right":null}},"right":{"nodeIndex":109,"featureIndex":-1,"threshold":0,"label":1,"left":null,"right":null}}}}}